mutwo/mmml_converters/__init__.py
mutwo/mmml_converters/configurations.py
mutwo/mmml_converters/mmml.py
mutwo.ext_mmml-0.3.3.dist-info/LICENSE
mutwo.ext_mmml-0.3.3.dist-info/METADATA
mutwo.ext_mmml-0.3.3.dist-info/WHEEL
mutwo.ext_mmml-0.3.3.dist-info/top_level.txt
mutwo.ext_mmml-0.3.3.dist-info/RECORD
