Metadata-Version: 2.1
Name: mutwo.ext-mmml
Version: 0.3.3
Summary: MMML extension for event based framework for generative art
Home-page: https://github.com/mutwo-org/mutwo.ext-mmml
Author: Levin Eric Zimmermann
Author-email: levin.eric.zimmermann@posteo.eu
License: GPL
Project-URL: Documentation, https://mutwo.readthedocs.io/en/latest/
Platform: UNKNOWN
Requires-Python: >=3.9, <4
License-File: LICENSE
Requires-Dist: mutwo.ext-core (<0.60.0,>=0.58.0)
Requires-Dist: mutwo.ext-music (<0.17.0,>=0.11.0)
Provides-Extra: testing
Requires-Dist: nose ; extra == 'testing'
Requires-Dist: coveralls ; extra == 'testing'
